pycliflo/__init__.py
pycliflo/core.py
pycliflo/datasets_mapping.py
pycliflo/data/adjectives.txt
pycliflo/data/nouns.txt
pycliflo/tests/__init__.py
pycliflo/tests/test_Cliflo.py
pycliflo-0.1.6.dist-info/METADATA
pycliflo-0.1.6.dist-info/WHEEL
pycliflo-0.1.6.dist-info/licenses/LICENSE
pycliflo-0.1.6.dist-info/RECORD
